badger_robot_connect/__init__.py
badger_robot_connect/badger_robot_connect.py
badger_robot_connect/gamepad_handler.py
badger_robot_connect/gui.py
badger_robot_connect/websocket_client.py
badger_robot_connect/images/BADGER.png
badger_robot_connect/images/Pitch_Indicator_Back.svg
badger_robot_connect/images/Pitch_Indicator_Needle.svg
badger_robot_connect/routes/route_internal_demo.txt
badger_robot_connect/routes/route_soccer.png
badger_robot_connect-0.0.15.dist-info/METADATA
badger_robot_connect-0.0.15.dist-info/RECORD
badger_robot_connect-0.0.15.dist-info/WHEEL
badger_robot_connect-0.0.15.dist-info/entry_points.txt
badger_robot_connect-0.0.15.dist-info/top_level.txt
