Metadata-Version: 2.1
Name: badger-robot-connect
Version: 0.0.15
Summary: Wireless Control Client for BADGER Robot
Home-page: UNKNOWN
Author: Tommy Vandermolen
Author-email: tommy.vandermolen@gmail.com
License: UNKNOWN
Platform: UNKNOWN
Classifier: Programming Language :: Python
Classifier: Programming Language :: Python :: 3
Classifier: Programming Language :: Python :: 3.6
Classifier: Programming Language :: Python :: Implementation :: CPython
Classifier: Programming Language :: Python :: Implementation :: PyPy
Requires-Python: >=3.6.0
Requires-Dist: numpy (>=1.14.3)
Requires-Dist: inputs
